{
"meta":{"test_sets":[],"test_metrics":[],"learn_metrics":[{"best_value":"Min","name":"RMSE"}],"launch_mode":"Train","parameters":"","iteration_count":200,"learn_sets":["learn"],"name":"experiment"},
"iterations":[
{"learn":[2.511372602],"iteration":0,"passed_time":0.06280041426,"remaining_time":12.49728244},
{"learn":[2.283524849],"iteration":1,"passed_time":0.0735777945,"remaining_time":7.284201655},
{"learn":[2.082446665],"iteration":2,"passed_time":0.07658229798,"remaining_time":5.028904234},
{"learn":[1.897288641],"iteration":3,"passed_time":0.08968528307,"remaining_time":4.39457887},
{"learn":[1.729451905],"iteration":4,"passed_time":0.09929840258,"remaining_time":3.8726377},
{"learn":[1.582103867],"iteration":5,"passed_time":0.1084687422,"remaining_time":3.507155997},
{"learn":[1.4479223],"iteration":6,"passed_time":0.1133237382,"remaining_time":3.124497352},
{"learn":[1.330631204],"iteration":7,"passed_time":0.1202147217,"remaining_time":2.88515332},
{"learn":[1.226257095],"iteration":8,"passed_time":0.1250148441,"remaining_time":2.653092803},
{"learn":[1.131600863],"iteration":9,"passed_time":0.1294548094,"remaining_time":2.459641379},
{"learn":[1.049011423],"iteration":10,"passed_time":0.1348033339,"remaining_time":2.316166374},
{"learn":[0.9785141027],"iteration":11,"passed_time":0.1391109278,"remaining_time":2.179404535},
{"learn":[0.9141569777],"iteration":12,"passed_time":0.1432695673,"remaining_time":2.060877622},
{"learn":[0.8580452279],"iteration":13,"passed_time":0.1484281385,"remaining_time":1.97197384},
{"learn":[0.8111372935],"iteration":14,"passed_time":0.1530693485,"remaining_time":1.887855298},
{"learn":[0.7669053072],"iteration":15,"passed_time":0.1574122747,"remaining_time":1.810241159},
{"learn":[0.7290630083],"iteration":16,"passed_time":0.1624870982,"remaining_time":1.749125822},
{"learn":[0.696569669],"iteration":17,"passed_time":0.1683234014,"remaining_time":1.701936614},
{"learn":[0.6693633234],"iteration":18,"passed_time":0.1729349455,"remaining_time":1.647432902},
{"learn":[0.6455923777],"iteration":19,"passed_time":0.1811464773,"remaining_time":1.630318295},
{"learn":[0.6240855376],"iteration":20,"passed_time":0.1854201137,"remaining_time":1.580485731},
{"learn":[0.6072631619],"iteration":21,"passed_time":0.1894519232,"remaining_time":1.532838288},
{"learn":[0.5932864498],"iteration":22,"passed_time":0.1936925605,"remaining_time":1.490590574},
{"learn":[0.5797217532],"iteration":23,"passed_time":0.1985112658,"remaining_time":1.455749282},
{"learn":[0.5682002941],"iteration":24,"passed_time":0.2043347777,"remaining_time":1.430343444},
{"learn":[0.5591440724],"iteration":25,"passed_time":0.2091032343,"remaining_time":1.399383183},
{"learn":[0.5509485503],"iteration":26,"passed_time":0.214305721,"remaining_time":1.373144064},
{"learn":[0.5433725492],"iteration":27,"passed_time":0.2190438034,"remaining_time":1.345554792},
{"learn":[0.5356495034],"iteration":28,"passed_time":0.2234251869,"remaining_time":1.317438171},
{"learn":[0.5300344278],"iteration":29,"passed_time":0.2281162706,"remaining_time":1.292658867},
{"learn":[0.5256581493],"iteration":30,"passed_time":0.2387389049,"remaining_time":1.301512095},
{"learn":[0.5214290596],"iteration":31,"passed_time":0.2443260898,"remaining_time":1.282711971},
{"learn":[0.5178824175],"iteration":32,"passed_time":0.2490400895,"remaining_time":1.260293786},
{"learn":[0.5142183666],"iteration":33,"passed_time":0.2532708521,"remaining_time":1.236557689},
{"learn":[0.5113223188],"iteration":34,"passed_time":0.2582105124,"remaining_time":1.21727813},
{"learn":[0.5082133201],"iteration":35,"passed_time":0.2634833306,"remaining_time":1.200312951},
{"learn":[0.5062425973],"iteration":36,"passed_time":0.2676888022,"remaining_time":1.179277696},
{"learn":[0.5034066009],"iteration":37,"passed_time":0.2720269369,"remaining_time":1.159693784},
{"learn":[0.5016496956],"iteration":38,"passed_time":0.2774588759,"remaining_time":1.145407154},
{"learn":[0.4994076386],"iteration":39,"passed_time":0.2824926588,"remaining_time":1.129970635},
{"learn":[0.4976035288],"iteration":40,"passed_time":0.2868458347,"remaining_time":1.11240214},
{"learn":[0.4959206793],"iteration":41,"passed_time":0.2921241111,"remaining_time":1.098943085},
{"learn":[0.4949597447],"iteration":42,"passed_time":0.2967953203,"remaining_time":1.08364803},
{"learn":[0.4936269454],"iteration":43,"passed_time":0.3011168304,"remaining_time":1.067596035},
{"learn":[0.4923478453],"iteration":44,"passed_time":0.3053053858,"remaining_time":1.05160744},
{"learn":[0.4906785642],"iteration":45,"passed_time":0.3164951301,"remaining_time":1.059570653},
{"learn":[0.4892416538],"iteration":46,"passed_time":0.3211458815,"remaining_time":1.045432338},
{"learn":[0.4883475051],"iteration":47,"passed_time":0.3268371469,"remaining_time":1.034984298},
{"learn":[0.4869193995],"iteration":48,"passed_time":0.3311692401,"remaining_time":1.020541944},
{"learn":[0.4845122644],"iteration":49,"passed_time":0.3353772116,"remaining_time":1.006131635},
{"learn":[0.4832059336],"iteration":50,"passed_time":0.3401744174,"remaining_time":0.9938429057},
{"learn":[0.4821021371],"iteration":51,"passed_time":0.3459118899,"remaining_time":0.9845184559},
{"learn":[0.4803228398],"iteration":52,"passed_time":0.3503871043,"remaining_time":0.9718283836},
{"learn":[0.4791173368],"iteration":53,"passed_time":0.3552443085,"remaining_time":0.9604753527},
{"learn":[0.478266243],"iteration":54,"passed_time":0.3608610759,"remaining_time":0.9513610184},
{"learn":[0.4771057914],"iteration":55,"passed_time":0.3662304332,"remaining_time":0.9417353997},
{"learn":[0.4763614856],"iteration":56,"passed_time":0.3720411955,"remaining_time":0.9333665079},
{"learn":[0.475342108],"iteration":57,"passed_time":0.3782877378,"remaining_time":0.9261527373},
{"learn":[0.4744847876],"iteration":58,"passed_time":0.3824752098,"remaining_time":0.9140509252},
{"learn":[0.4739950589],"iteration":59,"passed_time":0.3871148782,"remaining_time":0.9032680491},
{"learn":[0.473483521],"iteration":60,"passed_time":0.3924254037,"remaining_time":0.8942152642},
{"learn":[0.4729481774],"iteration":61,"passed_time":0.3968807853,"remaining_time":0.8833798124},
{"learn":[0.4719711746],"iteration":62,"passed_time":0.4015911601,"remaining_time":0.8733014116},
{"learn":[0.4707411868],"iteration":63,"passed_time":0.4069985997,"remaining_time":0.8648720244},
{"learn":[0.4702168582],"iteration":64,"passed_time":0.411540479,"remaining_time":0.8547379179},
{"learn":[0.4691238122],"iteration":65,"passed_time":0.416179939,"remaining_time":0.8449713914},
{"learn":[0.4685492185],"iteration":66,"passed_time":0.4217802485,"remaining_time":0.8372652695},
{"learn":[0.4680065124],"iteration":67,"passed_time":0.4262156723,"remaining_time":0.8273598345},
{"learn":[0.4671078582],"iteration":68,"passed_time":0.4308273831,"remaining_time":0.8179476403},
{"learn":[0.4666125557],"iteration":69,"passed_time":0.4358811238,"remaining_time":0.8094935156},
{"learn":[0.4657710085],"iteration":70,"passed_time":0.4423665347,"remaining_time":0.80373638},
{"learn":[0.4653791958],"iteration":71,"passed_time":0.4467363353,"remaining_time":0.7941979293},
{"learn":[0.4644806064],"iteration":72,"passed_time":0.4520631104,"remaining_time":0.7864659591},
{"learn":[0.4636024935],"iteration":73,"passed_time":0.4578801224,"remaining_time":0.779633722},
{"learn":[0.4626634424],"iteration":74,"passed_time":0.4619312231,"remaining_time":0.7698853718},
{"learn":[0.4622559012],"iteration":75,"passed_time":0.4657704544,"remaining_time":0.7599412677},
{"learn":[0.4616897632],"iteration":76,"passed_time":0.4717353792,"remaining_time":0.75355132},
{"learn":[0.4613827939],"iteration":77,"passed_time":0.4768308688,"remaining_time":0.7458123845},
{"learn":[0.4606850526],"iteration":78,"passed_time":0.4863622404,"remaining_time":0.7449345708},
{"learn":[0.4598984262],"iteration":79,"passed_time":0.4924084964,"remaining_time":0.7386127446},
{"learn":[0.4591431339],"iteration":80,"passed_time":0.4971781196,"remaining_time":0.7304221758},
{"learn":[0.4580361498],"iteration":81,"passed_time":0.5042979721,"remaining_time":0.7256970818},
{"learn":[0.4572031819],"iteration":82,"passed_time":0.5091341352,"remaining_time":0.7176951063},
{"learn":[0.4561714357],"iteration":83,"passed_time":0.5133381485,"remaining_time":0.7088955384},
{"learn":[0.4556434728],"iteration":84,"passed_time":0.5192042843,"remaining_time":0.7024528552},
{"learn":[0.4549797282],"iteration":85,"passed_time":0.5240394891,"remaining_time":0.6946569971},
{"learn":[0.454475303],"iteration":86,"passed_time":0.5283169171,"remaining_time":0.6862047314},
{"learn":[0.4536309559],"iteration":87,"passed_time":0.5333397419,"remaining_time":0.6787960351},
{"learn":[0.4528378728],"iteration":88,"passed_time":0.5397939454,"remaining_time":0.6732261566},
{"learn":[0.4524520637],"iteration":89,"passed_time":0.5444196141,"remaining_time":0.6654017506},
{"learn":[0.451963437],"iteration":90,"passed_time":0.5505796587,"remaining_time":0.6594855253},
{"learn":[0.4514825744],"iteration":91,"passed_time":0.5553434488,"remaining_time":0.6519249181},
{"learn":[0.450733541],"iteration":92,"passed_time":0.5599080358,"remaining_time":0.644195267},
{"learn":[0.4498571023],"iteration":93,"passed_time":0.5649110278,"remaining_time":0.6370273292},
{"learn":[0.448650929],"iteration":94,"passed_time":0.574662977,"remaining_time":0.6351538167},
{"learn":[0.4479627256],"iteration":95,"passed_time":0.5826802639,"remaining_time":0.6312369526},
{"learn":[0.4474494467],"iteration":96,"passed_time":0.588018247,"remaining_time":0.6243905097},
{"learn":[0.446838278],"iteration":97,"passed_time":0.5945841142,"remaining_time":0.6188528535},
{"learn":[0.4465019292],"iteration":98,"passed_time":0.6029635581,"remaining_time":0.6151446401},
{"learn":[0.4459777497],"iteration":99,"passed_time":0.6100128708,"remaining_time":0.6100128708},
{"learn":[0.4456582294],"iteration":100,"passed_time":0.6167497334,"remaining_time":0.6045368674},
{"learn":[0.4451363144],"iteration":101,"passed_time":0.6258721576,"remaining_time":0.6013281515},
{"learn":[0.4445536074],"iteration":102,"passed_time":0.6364769591,"remaining_time":0.5994006314},
{"learn":[0.4442895845],"iteration":103,"passed_time":0.6446478253,"remaining_time":0.595059531},
{"learn":[0.4436265442],"iteration":104,"passed_time":0.6499141853,"remaining_time":0.5880175962},
{"learn":[0.4431424627],"iteration":105,"passed_time":0.6594011832,"remaining_time":0.5847519926},
{"learn":[0.4424116859],"iteration":106,"passed_time":0.6647608324,"remaining_time":0.5777827796},
{"learn":[0.4411958358],"iteration":107,"passed_time":0.6711539125,"remaining_time":0.5717237032},
{"learn":[0.4403586097],"iteration":108,"passed_time":0.6809238195,"remaining_time":0.5684776842},
{"learn":[0.4395243809],"iteration":109,"passed_time":0.6887161957,"remaining_time":0.5634950692},
{"learn":[0.4391577647],"iteration":110,"passed_time":0.7004298844,"remaining_time":0.5616059434},
{"learn":[0.4385342096],"iteration":111,"passed_time":0.7119304121,"remaining_time":0.5593738952},
{"learn":[0.4374436261],"iteration":112,"passed_time":0.7267768092,"remaining_time":0.5595538265},
{"learn":[0.4370255875],"iteration":113,"passed_time":0.7360548543,"remaining_time":0.5552694515},
{"learn":[0.4365607462],"iteration":114,"passed_time":0.7466177402,"remaining_time":0.5518478949},
{"learn":[0.4361585499],"iteration":115,"passed_time":0.7546853591,"remaining_time":0.5464962945},
{"learn":[0.4358390414],"iteration":116,"passed_time":0.7696013794,"remaining_time":0.5459565341},
{"learn":[0.4354113343],"iteration":117,"passed_time":0.7780958203,"remaining_time":0.5407106548},
{"learn":[0.4346830901],"iteration":118,"passed_time":0.7914054249,"remaining_time":0.5386877262},
{"learn":[0.4338239109],"iteration":119,"passed_time":0.809460945,"remaining_time":0.53964063},
{"learn":[0.4330740864],"iteration":120,"passed_time":0.822580013,"remaining_time":0.5370563721},
{"learn":[0.4326688995],"iteration":121,"passed_time":0.8284031916,"remaining_time":0.5296348274},
{"learn":[0.4322247207],"iteration":122,"passed_time":0.8366927629,"remaining_time":0.5237832743},
{"learn":[0.4318136313],"iteration":123,"passed_time":0.8452614102,"remaining_time":0.5180634449},
{"learn":[0.4311539888],"iteration":124,"passed_time":0.8525483832,"remaining_time":0.5115290299},
{"learn":[0.430373499],"iteration":125,"passed_time":0.8645472309,"remaining_time":0.507749961},
{"learn":[0.4294061471],"iteration":126,"passed_time":0.8739946465,"remaining_time":0.5023748756},
{"learn":[0.429149942],"iteration":127,"passed_time":0.8866471019,"remaining_time":0.4987389948},
{"learn":[0.4285429083],"iteration":128,"passed_time":0.9048214939,"remaining_time":0.4980025276},
{"learn":[0.4280097671],"iteration":129,"passed_time":0.9101822681,"remaining_time":0.4900981444},
{"learn":[0.4275599955],"iteration":130,"passed_time":0.9212218913,"remaining_time":0.4852237443},
{"learn":[0.427095243],"iteration":131,"passed_time":0.9339842188,"remaining_time":0.4811433855},
{"learn":[0.42638288],"iteration":132,"passed_time":0.9415575175,"remaining_time":0.4743184487},
{"learn":[0.4258223443],"iteration":133,"passed_time":0.9575581756,"remaining_time":0.4716331313},
{"learn":[0.4250186932],"iteration":134,"passed_time":0.9818751543,"remaining_time":0.4727547039},
{"learn":[0.4242892397],"iteration":135,"passed_time":0.992986359,"remaining_time":0.4672876984},
{"learn":[0.4235408391],"iteration":136,"passed_time":0.9976193609,"remaining_time":0.4587592682},
{"learn":[0.4229962817],"iteration":137,"passed_time":1.007952253,"remaining_time":0.4528481136},
{"learn":[0.4224861678],"iteration":138,"passed_time":1.020590417,"remaining_time":0.4478850032},
{"learn":[0.4221590128],"iteration":139,"passed_time":1.02943539,"remaining_time":0.4411865959},
{"learn":[0.4217208525],"iteration":140,"passed_time":1.037405387,"remaining_time":0.4340916158},
{"learn":[0.4211426815],"iteration":141,"passed_time":1.045039851,"remaining_time":0.4268472629},
{"learn":[0.420569338],"iteration":142,"passed_time":1.052115496,"remaining_time":0.4193747081},
{"learn":[0.4201487364],"iteration":143,"passed_time":1.061799488,"remaining_time":0.4129220233},
{"learn":[0.4197404843],"iteration":144,"passed_time":1.082393358,"remaining_time":0.4105629978},
{"learn":[0.4191337545],"iteration":145,"passed_time":1.098587177,"remaining_time":0.4063267643},
{"learn":[0.4186683641],"iteration":146,"passed_time":1.110740938,"remaining_time":0.4004712225},
{"learn":[0.4181794404],"iteration":147,"passed_time":1.117529674,"remaining_time":0.3926455611},
{"learn":[0.4178405056],"iteration":148,"passed_time":1.124261412,"remaining_time":0.3848143087},
{"learn":[0.4170405546],"iteration":149,"passed_time":1.135420949,"remaining_time":0.3784736495},
{"learn":[0.4163350038],"iteration":150,"passed_time":1.145185397,"remaining_time":0.3716164534},
{"learn":[0.4158514392],"iteration":151,"passed_time":1.157060248,"remaining_time":0.3653874469},
{"learn":[0.4150495388],"iteration":152,"passed_time":1.164806251,"remaining_time":0.3578162993},
{"learn":[0.414772868],"iteration":153,"passed_time":1.174925232,"remaining_time":0.3509516926},
{"learn":[0.4141154556],"iteration":154,"passed_time":1.186204599,"remaining_time":0.3443819803},
{"learn":[0.4138788492],"iteration":155,"passed_time":1.196217374,"remaining_time":0.337394644},
{"learn":[0.4132701109],"iteration":156,"passed_time":1.221740404,"remaining_time":0.3346167986},
{"learn":[0.4127188785],"iteration":157,"passed_time":1.228494058,"remaining_time":0.3265617117},
{"learn":[0.4121387623],"iteration":158,"passed_time":1.23627306,"remaining_time":0.3187873928},
{"learn":[0.4117745658],"iteration":159,"passed_time":1.257257585,"remaining_time":0.3143143964},
{"learn":[0.4108769182],"iteration":160,"passed_time":1.273903601,"remaining_time":0.3085853444},
{"learn":[0.4103594235],"iteration":161,"passed_time":1.285458586,"remaining_time":0.3015273226},
{"learn":[0.4097506549],"iteration":162,"passed_time":1.293267878,"remaining_time":0.2935638742},
{"learn":[0.4091159111],"iteration":163,"passed_time":1.30143012,"remaining_time":0.2856797824},
{"learn":[0.4086318618],"iteration":164,"passed_time":1.309740399,"remaining_time":0.277823721},
{"learn":[0.4083220128],"iteration":165,"passed_time":1.317593357,"remaining_time":0.2698685189},
{"learn":[0.4079628317],"iteration":166,"passed_time":1.324301887,"remaining_time":0.2616883968},
{"learn":[0.4076917573],"iteration":167,"passed_time":1.335421383,"remaining_time":0.2543659777},
{"learn":[0.4071048602],"iteration":168,"passed_time":1.342213911,"remaining_time":0.2462049186},
{"learn":[0.4066866099],"iteration":169,"passed_time":1.352144064,"remaining_time":0.2386136583},
{"learn":[0.4062769903],"iteration":170,"passed_time":1.365415961,"remaining_time":0.2315617711},
{"learn":[0.4057128193],"iteration":171,"passed_time":1.371921288,"remaining_time":0.2233360236},
{"learn":[0.4051489523],"iteration":172,"passed_time":1.379970991,"remaining_time":0.2153711951},
{"learn":[0.4049426741],"iteration":173,"passed_time":1.389129331,"remaining_time":0.2075710494},
{"learn":[0.404465893],"iteration":174,"passed_time":1.405797054,"remaining_time":0.2008281506},
{"learn":[0.4037896042],"iteration":175,"passed_time":1.418493675,"remaining_time":0.1934309557},
{"learn":[0.4035133296],"iteration":176,"passed_time":1.425995726,"remaining_time":0.1852988796},
{"learn":[0.403025312],"iteration":177,"passed_time":1.433084204,"remaining_time":0.1771227668},
{"learn":[0.4025874303],"iteration":178,"passed_time":1.441707683,"remaining_time":0.1691388902},
{"learn":[0.4023076847],"iteration":179,"passed_time":1.451453758,"remaining_time":0.1612726397},
{"learn":[0.4019799931],"iteration":180,"passed_time":1.468347475,"remaining_time":0.1541359228},
{"learn":[0.401735002],"iteration":181,"passed_time":1.497206125,"remaining_time":0.148075331},
{"learn":[0.4012212206],"iteration":182,"passed_time":1.511871193,"remaining_time":0.1404470508},
{"learn":[0.4007457275],"iteration":183,"passed_time":1.527489153,"remaining_time":0.1328251438},
{"learn":[0.4002403039],"iteration":184,"passed_time":1.53800979,"remaining_time":0.1247034965},
{"learn":[0.4000222852],"iteration":185,"passed_time":1.549253408,"remaining_time":0.1166104716},
{"learn":[0.3993660059],"iteration":186,"passed_time":1.563784939,"remaining_time":0.1087123219},
{"learn":[0.398930021],"iteration":187,"passed_time":1.574636484,"remaining_time":0.1005087117},
{"learn":[0.3983023785],"iteration":188,"passed_time":1.582806017,"remaining_time":0.09212098509},
{"learn":[0.398044896],"iteration":189,"passed_time":1.59389018,"remaining_time":0.08388895686},
{"learn":[0.397639718],"iteration":190,"passed_time":1.611970491,"remaining_time":0.07595672473},
{"learn":[0.3971634277],"iteration":191,"passed_time":1.633316466,"remaining_time":0.06805485274},
{"learn":[0.3966401488],"iteration":192,"passed_time":1.654161453,"remaining_time":0.05999549313},
{"learn":[0.3961052632],"iteration":193,"passed_time":1.670383147,"remaining_time":0.05166133445},
{"learn":[0.3956510852],"iteration":194,"passed_time":1.692752844,"remaining_time":0.04340391909},
{"learn":[0.3951343302],"iteration":195,"passed_time":1.722604301,"remaining_time":0.03515518982},
{"learn":[0.3948755673],"iteration":196,"passed_time":1.730335721,"remaining_time":0.02635029016},
{"learn":[0.3945176716],"iteration":197,"passed_time":1.738130222,"remaining_time":0.01755687093},
{"learn":[0.3942442276],"iteration":198,"passed_time":1.747244438,"remaining_time":0.008780122803},
{"learn":[0.3938716166],"iteration":199,"passed_time":1.765394455,"remaining_time":0}
]}